pictologics/__init__.py
pictologics/features/__init__.py
pictologics/features/_utils.py
pictologics/features/intensity.py
pictologics/features/morphology.py
pictologics/features/texture.py
pictologics/filters/__init__.py
pictologics/filters/base.py
pictologics/filters/gabor.py
pictologics/filters/laws.py
pictologics/filters/log.py
pictologics/filters/mean.py
pictologics/filters/riesz.py
pictologics/filters/wavelets.py
pictologics/loader.py
pictologics/loaders/__init__.py
pictologics/loaders/seg_loader.py
pictologics/pipeline.py
pictologics/preprocessing.py
pictologics/results.py
pictologics/templates/__init__.py
pictologics/templates/standard_configs.yaml
pictologics/utilities/__init__.py
pictologics/utilities/dicom_database.py
pictologics/utilities/dicom_utils.py
pictologics/utilities/sr_parser.py
pictologics/utilities/visualization.py
pictologics/warmup.py
pictologics-0.3.1.dist-info/METADATA
pictologics-0.3.1.dist-info/WHEEL
pictologics-0.3.1.dist-info/licenses/LICENSE
pictologics-0.3.1.dist-info/licenses/NOTICE
pictologics-0.3.1.dist-info/RECORD
