Metadata-Version: 2.4
Name: pictologics
Version: 0.3.1
Summary: IBSI-compliant radiomic feature extraction package
License: Apache-2.0
License-File: LICENSE
License-File: NOTICE
Keywords: radiomics,medical-imaging,ibsi,dicom,nifti
Author: Márton Kolossváry
Author-email: marton.kolossvary@gmail.com
Requires-Python: >=3.12,<3.15
Classifier: Development Status :: 3 - Alpha
Classifier: Intended Audience :: Science/Research
Classifier: License :: OSI Approved :: Apache Software License
Classifier: Programming Language :: Python :: 3
Classifier: Programming Language :: Python :: 3.12
Classifier: Programming Language :: Python :: 3.13
Classifier: Programming Language :: Python :: 3.14
Classifier: Topic :: Scientific/Engineering :: Medical Science Apps.
Classifier: Typing :: Typed
Requires-Dist: Pillow (>=11.1.0,<12.0.0)
Requires-Dist: PyWavelets (>=1.4,<2.0)
Requires-Dist: highdicom (>=0.22.0)
Requires-Dist: matplotlib (>=3.10.0,<4.0.0)
Requires-Dist: nibabel (>=3.2.0)
Requires-Dist: numba (>=0.62.1,<0.63.0)
Requires-Dist: numpy (>=2.0,<2.3)
Requires-Dist: pandas (>=2.0.0)
Requires-Dist: pydicom (>=2.2.0)
Requires-Dist: pymcubes (>=0.1.6,<0.2.0)
Requires-Dist: pyyaml (>=6.0)
Requires-Dist: scipy (>=1.16.3,<2.0.0)
Requires-Dist: tqdm (>=4.66.0,<5.0.0)
Project-URL: Documentation, https://martonkolossvary.github.io/pictologics/
Project-URL: Homepage, https://martonkolossvary.github.io/pictologics/
Project-URL: Repository, https://github.com/martonkolossvary/pictologics
